LICENSE
README.md
setup.py
lptransportsolver/__init__.py
lptransportsolver/__main__.py
lptransportsolver.egg-info/PKG-INFO
lptransportsolver.egg-info/SOURCES.txt
lptransportsolver.egg-info/dependency_links.txt
lptransportsolver.egg-info/top_level.txt
lptransportsolver/Solver/__init__.py
lptransportsolver/Solver/core.py